{"v":"5.4.1","fr":60,"ip":0,"op":10800,"w":1920,"h":1080,"nm":"Bouncerback Main Title","ddd":0,"assets":[{"id":"comp_0","layers":[{"ddd":0,"ind":1,"ty":4,"nm":"Átomo 1","sr":1,"ks":{"o":{"a":0,"k":100,"ix":11},"r":{"a":0,"k":0,"ix":10},"p":{"a":1,"k":[{"i":{"x":0.833,"y":0.833},"o":{"x":0.167,"y":0.167},"n":"0p833_0p833_0p167_0p167","t":0,"s":[321.307,322.307,0],"e":[321.307,22.307,0],"to":[0,-50,0],"ti":[0,-50,0]},{"i":{"x":0.833,"y":0.833},"o":{"x":0.167,"y":0.167},"n":"0p833_0p833_0p167_0p167","t":60,"s":[321.307,22.307,0],"e":[321.307,622.307,0],"to":[0,50,0],"ti":[0,-50,0]},{"i":{"x":0.833,"y":0.833},"o":{"x":0.167,"y":0.167},"n":"0p833_0p833_0p167_0p167","t":180,"s":[321.307,622.307,0],"e":[321.307,322.307,0],"to":[0,50,0],"ti":[0,50,0]},{"t":240}],"ix":2},"a":{"a":0,"k":[0,0,0],"ix":1},"s":{"a":0,"k":[100,100,100],"ix":6}},"ao":0,"shapes":[{"ty":"gr","it":[{"d":1,"ty":"el","s":{"a":0,"k":[27.387,27.387],"ix":2},"p":{"a":0,"k":[0,0],"ix":3},"nm":"Trazado elíptico 1","mn":"ADBE Vector Shape - Ellipse","hd":false},{"ty":"st","c":{"a":0,"k":[1,1,1,1],"ix":3},"o":{"a":0,"k":100,"ix":4},"w":{"a":0,"k":170,"ix":5},"lc":1,"lj":1,"ml":4,"ml2":{"a":0,"k":4,"ix":8},"nm":"Trazo 1","mn":"ADBE Vector Graphic - Stroke","hd":true},{"ty":"fl","c":{"a":0,"k":[0.89411765337,0.890196084976,0.89411765337,1],"ix":4},"o":{"a":0,"k":100,"ix":5},"r":1,"nm":"Relleno 1","mn":"ADBE Vector Graphic - Fill","hd":false},{"ty":"tr","p":{"a":0,"k":[-1.307,-2.307],"ix":2},"a":{"a":0,"k":[0,0],"ix":1},"s":{"a":0,"k":[100,100],"ix":3},"r":{"a":0,"k":0,"ix":6},"o":{"a":0,"k":100,"ix":7},"sk":{"a":0,"k":0,"ix":4},"sa":{"a":0,"k":0,"ix":5},"nm":"Transformar"}],"nm":"Elipse 1","np":3,"cix":2,"ix":1,"mn":"ADBE Vector Group","hd":false}],"ip":0,"op":240,"st":0,"bm":0}]},{"id":"comp_1","layers":[{"ddd":0,"ind":1,"ty":0,"nm":"\rRecorrido del átomo 2","refId":"comp_0","sr":1,"ks":{"o":{"a":0,"k":100,"ix":11},"r":{"a":0,"k":60,"ix":10},"p":{"a":0,"k":[340,340,0],"ix":2},"a":{"a":0,"k":[320,320,0],"ix":1},"s":{"a":0,"k":[100,100,100],"ix":6}},"ao":0,"w":640,"h":640,"ip":-180,"op":60,"st":-180,"bm":0},{"ddd":0,"ind":2,"ty":0,"nm":"\rRecorrido del átomo 2","refId":"comp_0","sr":1,"ks":{"o":{"a":0,"k":100,"ix":11},"r":{"a":0,"k":-120,"ix":10},"p":{"a":0,"k":[340,340,0],"ix":2},"a":{"a":0,"k":[320,320,0],"ix":1},"s":{"a":0,"k":[100,100,100],"ix":6}},"ao":0,"w":640,"h":640,"ip":-180,"op":60,"st":-180,"bm":0},{"ddd":0,"ind":3,"ty":0,"nm":"\rRecorrido del átomo 2","refId":"comp_0","sr":1,"ks":{"o":{"a":0,"k":100,"ix":11},"r":{"a":0,"k":-120,"ix":10},"p":{"a":0,"k":[340,340,0],"ix":2},"a":{"a":0,"k":[320,320,0],"ix":1},"s":{"a":0,"k":[100,100,100],"ix":6}},"ao":0,"w":640,"h":640,"ip":60,"op":300,"st":60,"bm":0},{"ddd":0,"ind":4,"ty":0,"nm":"\rRecorrido del átomo 2","refId":"comp_0","sr":1,"ks":{"o":{"a":0,"k":100,"ix":11},"r":{"a":0,"k":60,"ix":10},"p":{"a":0,"k":[340,340,0],"ix":2},"a":{"a":0,"k":[320,320,0],"ix":1},"s":{"a":0,"k":[100,100,100],"ix":6}},"ao":0,"w":640,"h":640,"ip":60,"op":300,"st":60,"bm":0},{"ddd":0,"ind":5,"ty":0,"nm":"\rRecorrido del átomo 2","refId":"comp_0","sr":1,"ks":{"o":{"a":0,"k":100,"ix":11},"r":{"a":0,"k":180,"ix":10},"p":{"a":0,"k":[340,340,0],"ix":2},"a":{"a":0,"k":[320,320,0],"ix":1},"s":{"a":0,"k":[100,100,100],"ix":6}},"ao":0,"w":640,"h":640,"ip":0,"op":240,"st":0,"bm":0},{"ddd":0,"ind":6,"ty":0,"nm":"\rRecorrido del átomo 2","refId":"comp_0","sr":1,"ks":{"o":{"a":0,"k":100,"ix":11},"r":{"a":0,"k":0,"ix":10},"p":{"a":0,"k":[340,340,0],"ix":2},"a":{"a":0,"k":[320,320,0],"ix":1},"s":{"a":0,"k":[100,100,100],"ix":6}},"ao":0,"w":640,"h":640,"ip":0,"op":240,"st":0,"bm":0},{"ddd":0,"ind":7,"ty":4,"nm":"Pucks","sr":1,"ks":{"o":{"a":0,"k":100,"ix":11},"r":{"a":1,"k":[{"i":{"x":[0.231],"y":[0.998]},"o":{"x":[0.333],"y":[0]},"n":["0p231_0p998_0p333_0"],"t":0,"s":[-85],"e":[34]},{"i":{"x":[0.099],"y":[1.116]},"o":{"x":[0.793],"y":[-0.014]},"n":["0p099_1p116_0p793_-0p014"],"t":60,"s":[34],"e":[90]},{"i":{"x":[0.813],"y":[0.967]},"o":{"x":[1],"y":[0.081]},"n":["0p813_0p967_1_0p081"],"t":120,"s":[90],"e":[34]},{"i":{"x":[0.219],"y":[1.004]},"o":{"x":[0.654],"y":[0.047]},"n":["0p219_1p004_0p654_0p047"],"t":180,"s":[34],"e":[-85]},{"t":240}],"ix":10},"p":{"a":0,"k":[340,340,0],"ix":2},"a":{"a":0,"k":[320,320,0],"ix":1},"s":{"a":0,"k":[100,100,100],"ix":6}},"ao":0,"shapes":[{"ty":"gr","it":[{"ind":0,"ty":"sh","ix":1,"ks":{"a":0,"k":{"i":[[0,0],[19.434,-12.35],[22.8,-8.437]],"o":[[-16.405,16.158],[-19.433,12.35],[0,0]],"v":[[58.047,-36.827],[3.903,6.142],[-58.048,36.827]],"c":false},"ix":2},"nm":"Trazado 1","mn":"ADBE Vector Shape - Group","hd":false},{"ty":"st","c":{"a":0,"k":[0.89411765337,0.890196084976,0.89411765337,1],"ix":3},"o":{"a":0,"k":100,"ix":4},"w":{"a":0,"k":24,"ix":5},"lc":1,"lj":1,"ml":4,"ml2":{"a":0,"k":4,"ix":8},"nm":"Trazo 1","mn":"ADBE Vector Graphic - Stroke","hd":false},{"ty":"tr","p":{"a":0,"k":[496.537,585.233],"ix":2},"a":{"a":0,"k":[0,0],"ix":1},"s":{"a":0,"k":[100,100],"ix":3},"r":{"a":0,"k":0,"ix":6},"o":{"a":0,"k":100,"ix":7},"sk":{"a":0,"k":0,"ix":4},"sa":{"a":0,"k":0,"ix":5},"nm":"Transformar"}],"nm":"Grupo 2","np":2,"cix":2,"ix":1,"mn":"ADBE Vector Group","hd":false},{"ty":"gr","it":[{"ind":0,"ty":"sh","ix":1,"ks":{"a":0,"k":{"i":[[0,0],[-19.434,12.35],[-22.8,8.437]],"o":[[16.405,-16.158],[19.434,-12.35],[0,0]],"v":[[-58.048,36.827],[-3.904,-6.142],[58.048,-36.827]],"c":false},"ix":2},"nm":"Trazado 1","mn":"ADBE Vector Shape - Group","hd":false},{"ty":"st","c":{"a":0,"k":[0.89411765337,0.890196084976,0.89411765337,1],"ix":3},"o":{"a":0,"k":100,"ix":4},"w":{"a":0,"k":24,"ix":5},"lc":1,"lj":1,"ml":4,"ml2":{"a":0,"k":4,"ix":8},"nm":"Trazo 1","mn":"ADBE Vector Graphic - Stroke","hd":false},{"ty":"tr","p":{"a":0,"k":[149.753,50.742],"ix":2},"a":{"a":0,"k":[0,0],"ix":1},"s":{"a":0,"k":[100,100],"ix":3},"r":{"a":0,"k":0,"ix":6},"o":{"a":0,"k":100,"ix":7},"sk":{"a":0,"k":0,"ix":4},"sa":{"a":0,"k":0,"ix":5},"nm":"Transformar"}],"nm":"Grupo 3","np":2,"cix":2,"ix":2,"mn":"ADBE Vector Group","hd":false}],"ip":0,"op":240,"st":0,"bm":0},{"ddd":0,"ind":8,"ty":4,"nm":"GameSurface","sr":1,"ks":{"o":{"a":0,"k":100,"ix":11},"r":{"a":0,"k":0,"ix":10},"p":{"a":0,"k":[340,340,0],"ix":2},"a":{"a":0,"k":[320,320,0],"ix":1},"s":{"a":0,"k":[100,100,100],"ix":6}},"ao":0,"shapes":[{"ty":"gr","it":[{"ind":0,"ty":"sh","ix":1,"ks":{"a":0,"k":{"i":[[163.318,-60.435],[60.435,163.318],[-163.318,60.435],[-60.435,-163.318]],"o":[[-163.318,60.435],[-60.435,-163.318],[163.317,-60.435],[60.435,163.317]],"v":[[109.428,295.712],[-295.712,109.427],[-109.427,-295.712],[295.712,-109.428]],"c":true},"ix":2},"nm":"Trazado 1","mn":"ADBE Vector Shape - Group","hd":false},{"ty":"st","c":{"a":0,"k":[0.894000004787,0.889999988032,0.894000004787,1],"ix":3},"o":{"a":0,"k":100,"ix":4},"w":{"a":0,"k":8,"ix":5},"lc":1,"lj":1,"ml":4,"ml2":{"a":0,"k":4,"ix":8},"nm":"Trazo 1","mn":"ADBE Vector Graphic - Stroke","hd":false},{"ty":"tr","p":{"a":0,"k":[320,320],"ix":2},"a":{"a":0,"k":[0,0],"ix":1},"s":{"a":0,"k":[100,100],"ix":3},"r":{"a":0,"k":0,"ix":6},"o":{"a":0,"k":100,"ix":7},"sk":{"a":0,"k":0,"ix":4},"sa":{"a":0,"k":0,"ix":5},"nm":"Transformar"}],"nm":"Game Surface","np":2,"cix":2,"ix":1,"mn":"ADBE Vector Group","hd":false}],"ip":0,"op":240,"st":0,"bm":0}]},{"id":"comp_2","layers":[{"ddd":0,"ind":1,"ty":0,"nm":"Bouncerback gameSurface","refId":"comp_3","sr":1,"ks":{"o":{"a":0,"k":100,"ix":11},"r":{"a":0,"k":0,"ix":10},"p":{"a":0,"k":[340,340,0],"ix":2},"a":{"a":0,"k":[340,340,0],"ix":1},"s":{"a":0,"k":[100,100,100],"ix":6}},"ao":0,"w":680,"h":680,"ip":0,"op":480,"st":0,"bm":0}]},{"id":"comp_3","layers":[{"ddd":0,"ind":1,"ty":0,"nm":"\rRecorrido del átomo","refId":"comp_4","sr":1,"ks":{"o":{"a":0,"k":100,"ix":11},"r":{"a":0,"k":-120,"ix":10},"p":{"a":0,"k":[340,340,0],"ix":2},"a":{"a":0,"k":[320,320,0],"ix":1},"s":{"a":0,"k":[100,100,100],"ix":6}},"ao":0,"w":640,"h":640,"ip":0,"op":121,"st":-359,"bm":0},{"ddd":0,"ind":2,"ty":0,"nm":"\rRecorrido del átomo","refId":"comp_4","sr":1,"ks":{"o":{"a":0,"k":100,"ix":11},"r":{"a":0,"k":60,"ix":10},"p":{"a":0,"k":[340,340,0],"ix":2},"a":{"a":0,"k":[320,320,0],"ix":1},"s":{"a":0,"k":[100,100,100],"ix":6}},"ao":0,"w":640,"h":640,"ip":0,"op":121,"st":-359,"bm":0},{"ddd":0,"ind":3,"ty":0,"nm":"\rRecorrido del átomo","refId":"comp_4","sr":1,"ks":{"o":{"a":0,"k":100,"ix":11},"r":{"a":0,"k":-120,"ix":10},"p":{"a":0,"k":[340,340,0],"ix":2},"a":{"a":0,"k":[320,320,0],"ix":1},"s":{"a":0,"k":[100,100,100],"ix":6}},"ao":0,"w":640,"h":640,"ip":119,"op":480,"st":119,"bm":0},{"ddd":0,"ind":4,"ty":0,"nm":"\rRecorrido del átomo","refId":"comp_4","sr":1,"ks":{"o":{"a":0,"k":100,"ix":11},"r":{"a":0,"k":60,"ix":10},"p":{"a":0,"k":[340,340,0],"ix":2},"a":{"a":0,"k":[320,320,0],"ix":1},"s":{"a":0,"k":[100,100,100],"ix":6}},"ao":0,"w":640,"h":640,"ip":119,"op":480,"st":119,"bm":0},{"ddd":0,"ind":5,"ty":0,"nm":"\rRecorrido del átomo","refId":"comp_4","sr":1,"ks":{"o":{"a":0,"k":100,"ix":11},"r":{"a":0,"k":180,"ix":10},"p":{"a":0,"k":[340,340,0],"ix":2},"a":{"a":0,"k":[320,320,0],"ix":1},"s":{"a":0,"k":[100,100,100],"ix":6}},"ao":0,"w":640,"h":640,"ip":0,"op":480,"st":0,"bm":0},{"ddd":0,"ind":6,"ty":0,"nm":"\rRecorrido del átomo","refId":"comp_4","sr":1,"ks":{"o":{"a":0,"k":100,"ix":11},"r":{"a":0,"k":0,"ix":10},"p":{"a":0,"k":[340,340,0],"ix":2},"a":{"a":0,"k":[320,320,0],"ix":1},"s":{"a":0,"k":[100,100,100],"ix":6}},"ao":0,"w":640,"h":640,"ip":0,"op":480,"st":0,"bm":0},{"ddd":0,"ind":7,"ty":4,"nm":"Pucks","sr":1,"ks":{"o":{"a":0,"k":100,"ix":11},"r":{"a":1,"k":[{"i":{"x":[0.231],"y":[0.996]},"o":{"x":[0.333],"y":[0]},"n":["0p231_0p996_0p333_0"],"t":0,"s":[-85],"e":[34]},{"i":{"x":[0.099],"y":[1.238]},"o":{"x":[0.793],"y":[-0.028]},"n":["0p099_1p238_0p793_-0p028"],"t":119,"s":[34],"e":[90]},{"i":{"x":[0.813],"y":[0.935]},"o":{"x":[1],"y":[0.159]},"n":["0p813_0p935_1_0p159"],"t":242,"s":[90],"e":[34]},{"i":{"x":[0.219],"y":[1.009]},"o":{"x":[0.654],"y":[0.093]},"n":["0p219_1p009_0p654_0p093"],"t":360,"s":[34],"e":[-85]},{"t":479}],"ix":10},"p":{"a":0,"k":[340,340,0],"ix":2},"a":{"a":0,"k":[320,320,0],"ix":1},"s":{"a":0,"k":[100,100,100],"ix":6}},"ao":0,"shapes":[{"ty":"gr","it":[{"ind":0,"ty":"sh","ix":1,"ks":{"a":0,"k":{"i":[[0,0],[19.434,-12.35],[22.8,-8.437]],"o":[[-16.405,16.158],[-19.433,12.35],[0,0]],"v":[[58.047,-36.827],[3.903,6.142],[-58.048,36.827]],"c":false},"ix":2},"nm":"Trazado 1","mn":"ADBE Vector Shape - Group","hd":false},{"ty":"st","c":{"a":0,"k":[0.89411765337,0.890196084976,0.89411765337,1],"ix":3},"o":{"a":0,"k":100,"ix":4},"w":{"a":0,"k":24,"ix":5},"lc":1,"lj":1,"ml":4,"ml2":{"a":0,"k":4,"ix":8},"nm":"Trazo 1","mn":"ADBE Vector Graphic - Stroke","hd":false},{"ty":"tr","p":{"a":0,"k":[496.537,585.233],"ix":2},"a":{"a":0,"k":[0,0],"ix":1},"s":{"a":0,"k":[100,100],"ix":3},"r":{"a":0,"k":0,"ix":6},"o":{"a":0,"k":100,"ix":7},"sk":{"a":0,"k":0,"ix":4},"sa":{"a":0,"k":0,"ix":5},"nm":"Transformar"}],"nm":"Grupo 2","np":2,"cix":2,"ix":1,"mn":"ADBE Vector Group","hd":false},{"ty":"gr","it":[{"ind":0,"ty":"sh","ix":1,"ks":{"a":0,"k":{"i":[[0,0],[-19.434,12.35],[-22.8,8.437]],"o":[[16.405,-16.158],[19.434,-12.35],[0,0]],"v":[[-58.048,36.827],[-3.904,-6.142],[58.048,-36.827]],"c":false},"ix":2},"nm":"Trazado 1","mn":"ADBE Vector Shape - Group","hd":false},{"ty":"st","c":{"a":0,"k":[0.89411765337,0.890196084976,0.89411765337,1],"ix":3},"o":{"a":0,"k":100,"ix":4},"w":{"a":0,"k":24,"ix":5},"lc":1,"lj":1,"ml":4,"ml2":{"a":0,"k":4,"ix":8},"nm":"Trazo 1","mn":"ADBE Vector Graphic - Stroke","hd":false},{"ty":"tr","p":{"a":0,"k":[149.753,50.742],"ix":2},"a":{"a":0,"k":[0,0],"ix":1},"s":{"a":0,"k":[100,100],"ix":3},"r":{"a":0,"k":0,"ix":6},"o":{"a":0,"k":100,"ix":7},"sk":{"a":0,"k":0,"ix":4},"sa":{"a":0,"k":0,"ix":5},"nm":"Transformar"}],"nm":"Grupo 3","np":2,"cix":2,"ix":2,"mn":"ADBE Vector Group","hd":false}],"ip":0,"op":480,"st":0,"bm":0},{"ddd":0,"ind":8,"ty":4,"nm":"GameSurface","sr":1,"ks":{"o":{"a":0,"k":100,"ix":11},"r":{"a":0,"k":0,"ix":10},"p":{"a":0,"k":[340,340,0],"ix":2},"a":{"a":0,"k":[320,320,0],"ix":1},"s":{"a":0,"k":[100,100,100],"ix":6}},"ao":0,"shapes":[{"ty":"gr","it":[{"ind":0,"ty":"sh","ix":1,"ks":{"a":0,"k":{"i":[[163.318,-60.435],[60.435,163.318],[-163.318,60.435],[-60.435,-163.318]],"o":[[-163.318,60.435],[-60.435,-163.318],[163.317,-60.435],[60.435,163.317]],"v":[[109.428,295.712],[-295.712,109.427],[-109.427,-295.712],[295.712,-109.428]],"c":true},"ix":2},"nm":"Trazado 1","mn":"ADBE Vector Shape - Group","hd":false},{"ty":"st","c":{"a":0,"k":[0.894000004787,0.889999988032,0.894000004787,1],"ix":3},"o":{"a":0,"k":100,"ix":4},"w":{"a":0,"k":8,"ix":5},"lc":1,"lj":1,"ml":4,"ml2":{"a":0,"k":4,"ix":8},"nm":"Trazo 1","mn":"ADBE Vector Graphic - Stroke","hd":false},{"ty":"tr","p":{"a":0,"k":[320,320],"ix":2},"a":{"a":0,"k":[0,0],"ix":1},"s":{"a":0,"k":[100,100],"ix":3},"r":{"a":0,"k":0,"ix":6},"o":{"a":0,"k":100,"ix":7},"sk":{"a":0,"k":0,"ix":4},"sa":{"a":0,"k":0,"ix":5},"nm":"Transformar"}],"nm":"Game Surface","np":2,"cix":2,"ix":1,"mn":"ADBE Vector Group","hd":false}],"ip":0,"op":480,"st":0,"bm":0}]},{"id":"comp_4","layers":[{"ddd":0,"ind":1,"ty":4,"nm":"Átomo 1","sr":1,"ks":{"o":{"a":0,"k":100,"ix":11},"r":{"a":0,"k":0,"ix":10},"p":{"a":1,"k":[{"i":{"x":0.833,"y":0.833},"o":{"x":0.167,"y":0.167},"n":"0p833_0p833_0p167_0p167","t":0,"s":[321.307,322.307,0],"e":[321.307,22.307,0],"to":[0,-50,0],"ti":[0,-50,0]},{"i":{"x":0.833,"y":0.833},"o":{"x":0.167,"y":0.167},"n":"0p833_0p833_0p167_0p167","t":120,"s":[321.307,22.307,0],"e":[321.307,622.307,0],"to":[0,50,0],"ti":[0,-50,0]},{"i":{"x":0.833,"y":0.833},"o":{"x":0.167,"y":0.167},"n":"0p833_0p833_0p167_0p167","t":360,"s":[321.307,622.307,0],"e":[321.307,322.307,0],"to":[0,50,0],"ti":[0,50,0]},{"t":480}],"ix":2},"a":{"a":0,"k":[0,0,0],"ix":1},"s":{"a":0,"k":[100,100,100],"ix":6}},"ao":0,"shapes":[{"ty":"gr","it":[{"d":1,"ty":"el","s":{"a":0,"k":[27.387,27.387],"ix":2},"p":{"a":0,"k":[0,0],"ix":3},"nm":"Trazado elíptico 1","mn":"ADBE Vector Shape - Ellipse","hd":false},{"ty":"st","c":{"a":0,"k":[1,1,1,1],"ix":3},"o":{"a":0,"k":100,"ix":4},"w":{"a":0,"k":170,"ix":5},"lc":1,"lj":1,"ml":4,"ml2":{"a":0,"k":4,"ix":8},"nm":"Trazo 1","mn":"ADBE Vector Graphic - Stroke","hd":true},{"ty":"fl","c":{"a":0,"k":[0.89411765337,0.890196084976,0.89411765337,1],"ix":4},"o":{"a":0,"k":100,"ix":5},"r":1,"nm":"Relleno 1","mn":"ADBE Vector Graphic - Fill","hd":false},{"ty":"tr","p":{"a":0,"k":[-1.307,-2.307],"ix":2},"a":{"a":0,"k":[0,0],"ix":1},"s":{"a":0,"k":[100,100],"ix":3},"r":{"a":0,"k":0,"ix":6},"o":{"a":0,"k":100,"ix":7},"sk":{"a":0,"k":0,"ix":4},"sa":{"a":0,"k":0,"ix":5},"nm":"Transformar"}],"nm":"Elipse 1","np":3,"cix":2,"ix":1,"mn":"ADBE Vector Group","hd":false}],"ip":0,"op":480,"st":0,"bm":0}]},{"id":"comp_5","layers":[{"ddd":0,"ind":1,"ty":0,"nm":"Bouncerback grid","refId":"comp_6","sr":1,"ks":{"o":{"a":0,"k":100,"ix":11},"r":{"a":0,"k":0,"ix":10},"p":{"a":0,"k":[960,540,0],"ix":2},"a":{"a":0,"k":[347.5,347.5,0],"ix":1},"s":{"a":0,"k":[134.741,134.741,100],"ix":6}},"ao":0,"w":695,"h":695,"ip":0,"op":3600,"st":0,"bm":0},{"ddd":0,"ind":2,"ty":0,"nm":"Bouncerback grid","refId":"comp_6","sr":1,"ks":{"o":{"a":0,"k":100,"ix":11},"r":{"a":0,"k":180,"ix":10},"p":{"a":0,"k":[960,540,0],"ix":2},"a":{"a":0,"k":[347.5,347.5,0],"ix":1},"s":{"a":0,"k":[134.741,134.741,100],"ix":6}},"ao":0,"w":695,"h":695,"ip":0,"op":3600,"st":0,"bm":0}]},{"id":"comp_6","layers":[{"ddd":0,"ind":1,"ty":4,"nm":"Bouncerback grid contornos","sr":1,"ks":{"o":{"a":0,"k":100,"ix":11},"r":{"a":0,"k":0,"ix":10},"p":{"a":0,"k":[347.5,347.5,0],"ix":2},"a":{"a":0,"k":[347.5,347.5,0],"ix":1},"s":{"a":0,"k":[100,100,100],"ix":6}},"ao":0,"shapes":[{"ty":"gr","it":[{"ind":0,"ty":"sh","ix":1,"ks":{"a":0,"k":{"i":[[0,-31.311],[31.311,0],[0,31.311],[-31.311,0]],"o":[[0,31.311],[-31.311,0],[0,-31.311],[31.311,0]],"v":[[56.693,0],[0,56.693],[-56.693,0],[0,-56.693]],"c":true},"ix":2},"nm":"Trazado 1","mn":"ADBE Vector Shape - Group","hd":false},{"ty":"st","c":{"a":0,"k":[0.8,0.8,0.8,1],"ix":3},"o":{"a":0,"k":100,"ix":4},"w":{"a":0,"k":5,"ix":5},"lc":1,"lj":1,"ml":4,"ml2":{"a":0,"k":4,"ix":8},"nm":"Trazo 1","mn":"ADBE Vector Graphic - Stroke","hd":false},{"ty":"tr","p":{"a":1,"k":[{"i":{"x":0.667,"y":1},"o":{"x":0.167,"y":0.167},"n":"0p667_1_0p167_0p167","t":1.57,"s":[347.244,344.779],"e":[347.244,63.779],"to":[0,-46.8333320617676],"ti":[0,46.8333320617676]},{"t":241}],"ix":2},"a":{"a":0,"k":[0,0],"ix":1},"s":{"a":0,"k":[100,100],"ix":3},"r":{"a":0,"k":0,"ix":6},"o":{"a":1,"k":[{"i":{"x":[0.833],"y":[0.833]},"o":{"x":[0.167],"y":[0.167]},"n":["0p833_0p833_0p167_0p167"],"t":540,"s":[100],"e":[0]},{"i":{"x":[0.833],"y":[0.833]},"o":{"x":[0.167],"y":[0.167]},"n":["0p833_0p833_0p167_0p167"],"t":546,"s":[0],"e":[100]},{"i":{"x":[0.833],"y":[0.833]},"o":{"x":[0.167],"y":[0.167]},"n":["0p833_0p833_0p167_0p167"],"t":557,"s":[100],"e":[100]},{"i":{"x":[0.833],"y":[0.833]},"o":{"x":[0.167],"y":[0.167]},"n":["0p833_0p833_0p167_0p167"],"t":564,"s":[100],"e":[0]},{"i":{"x":[0.833],"y":[0.833]},"o":{"x":[0.167],"y":[0.167]},"n":["0p833_0p833_0p167_0p167"],"t":567,"s":[0],"e":[100]},{"i":{"x":[0.833],"y":[0.833]},"o":{"x":[0.167],"y":[0.167]},"n":["0p833_0p833_0p167_0p167"],"t":573,"s":[100],"e":[0]},{"t":576}],"ix":7},"sk":{"a":0,"k":0,"ix":4},"sa":{"a":0,"k":0,"ix":5},"nm":"Transformar"}],"nm":"Grupo 1","np":2,"cix":2,"ix":1,"mn":"ADBE Vector Group","hd":false},{"ty":"gr","it":[{"ind":0,"ty":"sh","ix":1,"ks":{"a":0,"k":{"i":[[0,46.966],[-46.966,0],[0,-46.966],[46.966,0]],"o":[[0,-46.966],[46.966,0],[0,46.966],[-46.966,0]],"v":[[-85.039,0],[0,-85.039],[85.039,0],[0,85.039]],"c":true},"ix":2},"nm":"Trazado 1","mn":"ADBE Vector Shape - Group","hd":false},{"ty":"st","c":{"a":0,"k":[0.8,0.8,0.8,1],"ix":3},"o":{"a":0,"k":100,"ix":4},"w":{"a":0,"k":5.1,"ix":5},"lc":1,"lj":1,"ml":4,"ml2":{"a":0,"k":4,"ix":8},"nm":"Trazo 1","mn":"ADBE Vector Graphic - Stroke","hd":false},{"ty":"tr","p":{"a":1,"k":[{"i":{"x":0.667,"y":1},"o":{"x":0.167,"y":0.167},"n":"0p667_1_0p167_0p167","t":1.57,"s":[347.244,344.126],"e":[347.244,92.126],"to":[0,-42],"ti":[0,42]},{"t":241}],"ix":2},"a":{"a":0,"k":[0,0],"ix":1},"s":{"a":0,"k":[100,100],"ix":3},"r":{"a":0,"k":0,"ix":6},"o":{"a":1,"k":[{"i":{"x":[0.833],"y":[0.833]},"o":{"x":[0.167],"y":[0.167]},"n":["0p833_0p833_0p167_0p167"],"t":698,"s":[100],"e":[0]},{"i":{"x":[0.833],"y":[0.833]},"o":{"x":[0.167],"y":[0.167]},"n":["0p833_0p833_0p167_0p167"],"t":704,"s":[0],"e":[100]},{"i":{"x":[0.833],"y":[0.833]},"o":{"x":[0.167],"y":[0.167]},"n":["0p833_0p833_0p167_0p167"],"t":715,"s":[100],"e":[100]},{"i":{"x":[0.833],"y":[0.833]},"o":{"x":[0.167],"y":[0.167]},"n":["0p833_0p833_0p167_0p167"],"t":722,"s":[100],"e":[0]},{"i":{"x":[0.833],"y":[0.833]},"o":{"x":[0.167],"y":[0.167]},"n":["0p833_0p833_0p167_0p167"],"t":725,"s":[0],"e":[100]},{"i":{"x":[0.833],"y":[0.833]},"o":{"x":[0.167],"y":[0.167]},"n":["0p833_0p833_0p167_0p167"],"t":731,"s":[100],"e":[0]},{"t":734}],"ix":7},"sk":{"a":0,"k":0,"ix":4},"sa":{"a":0,"k":0,"ix":5},"nm":"Transformar"}],"nm":"Grupo 2","np":2,"cix":2,"ix":2,"mn":"ADBE Vector Group","hd":false},{"ty":"gr","it":[{"ind":0,"ty":"sh","ix":1,"ks":{"a":0,"k":{"i":[[0,62.621],[-62.621,0],[0,-62.621],[62.621,0]],"o":[[0,-62.621],[62.621,0],[0,62.621],[-62.621,0]],"v":[[-113.386,0],[0,-113.386],[113.386,0],[0,113.386]],"c":true},"ix":2},"nm":"Trazado 1","mn":"ADBE Vector Shape - Group","hd":false},{"ty":"st","c":{"a":0,"k":[0.8,0.8,0.8,1],"ix":3},"o":{"a":0,"k":100,"ix":4},"w":{"a":0,"k":5.2,"ix":5},"lc":1,"lj":1,"ml":4,"ml2":{"a":0,"k":4,"ix":8},"nm":"Trazo 1","mn":"ADBE Vector Graphic - Stroke","hd":false},{"ty":"tr","p":{"a":1,"k":[{"i":{"x":0.667,"y":1},"o":{"x":0.167,"y":0.167},"n":"0p667_1_0p167_0p167","t":1.57,"s":[347.244,343.472],"e":[347.244,120.472],"to":[0,-37.1666679382324],"ti":[0,37.1666679382324]},{"t":240.958984375}],"ix":2},"a":{"a":0,"k":[0,0],"ix":1},"s":{"a":0,"k":[100,100],"ix":3},"r":{"a":0,"k":0,"ix":6},"o":{"a":1,"k":[{"i":{"x":[0.833],"y":[0.833]},"o":{"x":[0.167],"y":[0.167]},"n":["0p833_0p833_0p167_0p167"],"t":568,"s":[100],"e":[0]},{"i":{"x":[0.833],"y":[0.833]},"o":{"x":[0.167],"y":[0.167]},"n":["0p833_0p833_0p167_0p167"],"t":574,"s":[0],"e":[100]},{"i":{"x":[0.833],"y":[0.833]},"o":{"x":[0.167],"y":[0.167]},"n":["0p833_0p833_0p167_0p167"],"t":585,"s":[100],"e":[100]},{"i":{"x":[0.833],"y":[0.833]},"o":{"x":[0.167],"y":[0.167]},"n":["0p833_0p833_0p167_0p167"],"t":592,"s":[100],"e":[0]},{"i":{"x":[0.833],"y":[0.833]},"o":{"x":[0.167],"y":[0.167]},"n":["0p833_0p833_0p167_0p167"],"t":595,"s":[0],"e":[100]},{"i":{"x":[0.833],"y":[0.833]},"o":{"x":[0.167],"y":[0.167]},"n":["0p833_0p833_0p167_0p167"],"t":601,"s":[100],"e":[0]},{"t":604}],"ix":7},"sk":{"a":0,"k":0,"ix":4},"sa":{"a":0,"k":0,"ix":5},"nm":"Transformar"}],"nm":"Grupo 3","np":2,"cix":2,"ix":3,"mn":"ADBE Vector Group","hd":false},{"ty":"gr","it":[{"ind":0,"ty":"sh","ix":1,"ks":{"a":0,"k":{"i":[[0,78.277],[-78.276,0],[0,-78.277],[78.277,0]],"o":[[0,-78.277],[78.277,0],[0,78.277],[-78.276,0]],"v":[[-141.732,0],[-0.001,-141.732],[141.732,0],[-0.001,141.732]],"c":true},"ix":2},"nm":"Trazado 1","mn":"ADBE Vector Shape - Group","hd":false},{"ty":"st","c":{"a":0,"k":[0.8,0.8,0.8,1],"ix":3},"o":{"a":0,"k":100,"ix":4},"w":{"a":0,"k":5.3,"ix":5},"lc":1,"lj":1,"ml":4,"ml2":{"a":0,"k":4,"ix":8},"nm":"Trazo 1","mn":"ADBE Vector Graphic - Stroke","hd":false},{"ty":"tr","p":{"a":1,"k":[{"i":{"x":0.667,"y":1},"o":{"x":0.167,"y":0.167},"n":"0p667_1_0p167_0p167","t":1.57,"s":[347.244,344.819],"e":[347.244,148.819],"to":[0,-32.6666679382324],"ti":[0,32.6666679382324]},{"t":241}],"ix":2},"a":{"a":0,"k":[0,0],"ix":1},"s":{"a":0,"k":[100,100],"ix":3},"r":{"a":0,"k":0,"ix":6},"o":{"a":1,"k":[{"i":{"x":[0.833],"y":[0.833]},"o":{"x":[0.167],"y":[0.167]},"n":["0p833_0p833_0p167_0p167"],"t":612,"s":[100],"e":[0]},{"i":{"x":[0.833],"y":[0.833]},"o":{"x":[0.167],"y":[0.167]},"n":["0p833_0p833_0p167_0p167"],"t":618,"s":[0],"e":[100]},{"i":{"x":[0.833],"y":[0.833]},"o":{"x":[0.167],"y":[0.167]},"n":["0p833_0p833_0p167_0p167"],"t":629,"s":[100],"e":[100]},{"i":{"x":[0.833],"y":[0.833]},"o":{"x":[0.167],"y":[0.167]},"n":["0p833_0p833_0p167_0p167"],"t":636,"s":[100],"e":[0]},{"i":{"x":[0.833],"y":[0.833]},"o":{"x":[0.167],"y":[0.167]},"n":["0p833_0p833_0p167_0p167"],"t":639,"s":[0],"e":[100]},{"i":{"x":[0.833],"y":[0.833]},"o":{"x":[0.167],"y":[0.167]},"n":["0p833_0p833_0p167_0p167"],"t":645,"s":[100],"e":[0]},{"t":648}],"ix":7},"sk":{"a":0,"k":0,"ix":4},"sa":{"a":0,"k":0,"ix":5},"nm":"Transformar"}],"nm":"Grupo 4","np":2,"cix":2,"ix":4,"mn":"ADBE Vector Group","hd":false},{"ty":"gr","it":[{"ind":0,"ty":"sh","ix":1,"ks":{"a":0,"k":{"i":[[0,93.932],[-93.932,0],[0,-93.932],[93.932,0]],"o":[[0,-93.932],[93.932,0],[0,93.932],[-93.932,0]],"v":[[-170.078,0],[0,-170.079],[170.078,0],[0,170.079]],"c":true},"ix":2},"nm":"Trazado 1","mn":"ADBE Vector Shape - Group","hd":false},{"ty":"st","c":{"a":0,"k":[0.8,0.8,0.8,1],"ix":3},"o":{"a":0,"k":100,"ix":4},"w":{"a":0,"k":5.4,"ix":5},"lc":1,"lj":1,"ml":4,"ml2":{"a":0,"k":4,"ix":8},"nm":"Trazo 1","mn":"ADBE Vector Graphic - Stroke","hd":false},{"ty":"tr","p":{"a":1,"k":[{"i":{"x":0.667,"y":1},"o":{"x":0.167,"y":0.167},"n":"0p667_1_0p167_0p167","t":1.57,"s":[347.244,348.165],"e":[347.244,177.165],"to":[0,-28.5000019073486],"ti":[0,28.5000019073486]},{"t":240.958984375}],"ix":2},"a":{"a":0,"k":[0,0],"ix":1},"s":{"a":0,"k":[100,100],"ix":3},"r":{"a":0,"k":0,"ix":6},"o":{"a":1,"k":[{"i":{"x":[0.833],"y":[0.833]},"o":{"x":[0.167],"y":[0.167]},"n":["0p833_0p833_0p167_0p167"],"t":1002,"s":[100],"e":[0]},{"i":{"x":[0.833],"y":[0.833]},"o":{"x":[0.167],"y":[0.167]},"n":["0p833_0p833_0p167_0p167"],"t":1008,"s":[0],"e":[100]},{"i":{"x":[0.833],"y":[0.833]},"o":{"x":[0.167],"y":[0.167]},"n":["0p833_0p833_0p167_0p167"],"t":1019,"s":[100],"e":[100]},{"i":{"x":[0.833],"y":[0.833]},"o":{"x":[0.167],"y":[0.167]},"n":["0p833_0p833_0p167_0p167"],"t":1026,"s":[100],"e":[0]},{"i":{"x":[0.833],"y":[0.833]},"o":{"x":[0.167],"y":[0.167]},"n":["0p833_0p833_0p167_0p167"],"t":1029,"s":[0],"e":[100]},{"i":{"x":[0.833],"y":[0.833]},"o":{"x":[0.167],"y":[0.167]},"n":["0p833_0p833_0p167_0p167"],"t":1035,"s":[100],"e":[0]},{"t":1038}],"ix":7},"sk":{"a":0,"k":0,"ix":4},"sa":{"a":0,"k":0,"ix":5},"nm":"Transformar"}],"nm":"Grupo 5","np":2,"cix":2,"ix":5,"mn":"ADBE Vector Group","hd":false},{"ty":"gr","it":[{"ind":0,"ty":"sh","ix":1,"ks":{"a":0,"k":{"i":[[0,109.587],[-109.587,0],[0,-109.587],[109.587,0]],"o":[[0,-109.587],[109.587,0],[0,109.587],[-109.587,0]],"v":[[-198.425,0],[0,-198.425],[198.425,0],[0,198.425]],"c":true},"ix":2},"nm":"Trazado 1","mn":"ADBE Vector Shape - Group","hd":false},{"ty":"st","c":{"a":0,"k":[0.8,0.8,0.8,1],"ix":3},"o":{"a":0,"k":100,"ix":4},"w":{"a":0,"k":5.5,"ix":5},"lc":1,"lj":1,"ml":4,"ml2":{"a":0,"k":4,"ix":8},"nm":"Trazo 1","mn":"ADBE Vector Graphic - Stroke","hd":false},{"ty":"tr","p":{"a":1,"k":[{"i":{"x":0.667,"y":1},"o":{"x":0.167,"y":0.167},"n":"0p667_1_0p167_0p167","t":1.57,"s":[347.244,346.512],"e":[347.244,206.512],"to":[0,-23.3333339691162],"ti":[0,23.3333339691162]},{"t":241}],"ix":2},"a":{"a":0,"k":[0,0],"ix":1},"s":{"a":0,"k":[100,100],"ix":3},"r":{"a":0,"k":0,"ix":6},"o":{"a":1,"k":[{"i":{"x":[0.833],"y":[0.833]},"o":{"x":[0.167],"y":[0.167]},"n":["0p833_0p833_0p167_0p167"],"t":662,"s":[100],"e":[0]},{"i":{"x":[0.833],"y":[0.833]},"o":{"x":[0.167],"y":[0.167]},"n":["0p833_0p833_0p167_0p167"],"t":668,"s":[0],"e":[100]},{"i":{"x":[0.833],"y":[0.833]},"o":{"x":[0.167],"y":[0.167]},"n":["0p833_0p833_0p167_0p167"],"t":679,"s":[100],"e":[100]},{"i":{"x":[0.833],"y":[0.833]},"o":{"x":[0.167],"y":[0.167]},"n":["0p833_0p833_0p167_0p167"],"t":686,"s":[100],"e":[0]},{"i":{"x":[0.833],"y":[0.833]},"o":{"x":[0.167],"y":[0.167]},"n":["0p833_0p833_0p167_0p167"],"t":689,"s":[0],"e":[100]},{"i":{"x":[0.833],"y":[0.833]},"o":{"x":[0.167],"y":[0.167]},"n":["0p833_0p833_0p167_0p167"],"t":695,"s":[100],"e":[0]},{"t":698}],"ix":7},"sk":{"a":0,"k":0,"ix":4},"sa":{"a":0,"k":0,"ix":5},"nm":"Transformar"}],"nm":"Grupo 6","np":2,"cix":2,"ix":6,"mn":"ADBE Vector Group","hd":false},{"ty":"gr","it":[{"ind":0,"ty":"sh","ix":1,"ks":{"a":0,"k":{"i":[[0,125.243],[-125.243,0],[0,-125.243],[125.242,0]],"o":[[0,-125.243],[125.242,0],[0,125.243],[-125.243,0]],"v":[[-226.771,0],[0.001,-226.772],[226.771,0],[0.001,226.772]],"c":true},"ix":2},"nm":"Trazado 1","mn":"ADBE Vector Shape - Group","hd":false},{"ty":"st","c":{"a":0,"k":[0.8,0.8,0.8,1],"ix":3},"o":{"a":0,"k":100,"ix":4},"w":{"a":0,"k":5.6,"ix":5},"lc":1,"lj":1,"ml":4,"ml2":{"a":0,"k":4,"ix":8},"nm":"Trazo 1","mn":"ADBE Vector Graphic - Stroke","hd":false},{"ty":"tr","p":{"a":1,"k":[{"i":{"x":0.667,"y":1},"o":{"x":0.167,"y":0.167},"n":"0p667_1_0p167_0p167","t":1.57,"s":[347.244,346.858],"e":[347.244,234.858],"to":[0,-18.6666660308838],"ti":[0,18.6666660308838]},{"t":240.958984375}],"ix":2},"a":{"a":0,"k":[0,0],"ix":1},"s":{"a":0,"k":[100,100],"ix":3},"r":{"a":0,"k":0,"ix":6},"o":{"a":1,"k":[{"i":{"x":[0.833],"y":[0.833]},"o":{"x":[0.167],"y":[0.167]},"n":["0p833_0p833_0p167_0p167"],"t":584,"s":[100],"e":[0]},{"i":{"x":[0.833],"y":[0.833]},"o":{"x":[0.167],"y":[0.167]},"n":["0p833_0p833_0p167_0p167"],"t":590,"s":[0],"e":[100]},{"i":{"x":[0.833],"y":[0.833]},"o":{"x":[0.167],"y":[0.167]},"n":["0p833_0p833_0p167_0p167"],"t":601,"s":[100],"e":[100]},{"i":{"x":[0.833],"y":[0.833]},"o":{"x":[0.167],"y":[0.167]},"n":["0p833_0p833_0p167_0p167"],"t":608,"s":[100],"e":[0]},{"i":{"x":[0.833],"y":[0.833]},"o":{"x":[0.167],"y":[0.167]},"n":["0p833_0p833_0p167_0p167"],"t":611,"s":[0],"e":[100]},{"i":{"x":[0.833],"y":[0.833]},"o":{"x":[0.167],"y":[0.167]},"n":["0p833_0p833_0p167_0p167"],"t":617,"s":[100],"e":[0]},{"t":620}],"ix":7},"sk":{"a":0,"k":0,"ix":4},"sa":{"a":0,"k":0,"ix":5},"nm":"Transformar"}],"nm":"Grupo 7","np":2,"cix":2,"ix":7,"mn":"ADBE Vector Group","hd":false},{"ty":"gr","it":[{"ind":0,"ty":"sh","ix":1,"ks":{"a":0,"k":{"i":[[0,140.898],[-140.898,0],[0,-140.898],[140.898,0]],"o":[[0,-140.898],[140.898,0],[0,140.898],[-140.898,0]],"v":[[-255.118,0],[0,-255.118],[255.118,0],[0,255.118]],"c":true},"ix":2},"nm":"Trazado 1","mn":"ADBE Vector Shape - Group","hd":false},{"ty":"st","c":{"a":0,"k":[0.8,0.8,0.8,1],"ix":3},"o":{"a":0,"k":100,"ix":4},"w":{"a":0,"k":5.7,"ix":5},"lc":1,"lj":1,"ml":4,"ml2":{"a":0,"k":4,"ix":8},"nm":"Trazo 1","mn":"ADBE Vector Graphic - Stroke","hd":false},{"ty":"tr","p":{"a":1,"k":[{"i":{"x":0.667,"y":1},"o":{"x":0.167,"y":0.167},"n":"0p667_1_0p167_0p167","t":1.57,"s":[347.244,346.204],"e":[347.244,263.204],"to":[0,-13.8333330154419],"ti":[0,13.8333330154419]},{"t":240.958984375}],"ix":2},"a":{"a":0,"k":[0,0],"ix":1},"s":{"a":0,"k":[100,100],"ix":3},"r":{"a":0,"k":0,"ix":6},"o":{"a":1,"k":[{"i":{"x":[0.833],"y":[0.833]},"o":{"x":[0.167],"y":[0.167]},"n":["0p833_0p833_0p167_0p167"],"t":742,"s":[100],"e":[0]},{"i":{"x":[0.833],"y":[0.833]},"o":{"x":[0.167],"y":[0.167]},"n":["0p833_0p833_0p167_0p167"],"t":748,"s":[0],"e":[100]},{"i":{"x":[0.833],"y":[0.833]},"o":{"x":[0.167],"y":[0.167]},"n":["0p833_0p833_0p167_0p167"],"t":759,"s":[100],"e":[100]},{"i":{"x":[0.833],"y":[0.833]},"o":{"x":[0.167],"y":[0.167]},"n":["0p833_0p833_0p167_0p167"],"t":766,"s":[100],"e":[0]},{"i":{"x":[0.833],"y":[0.833]},"o":{"x":[0.167],"y":[0.167]},"n":["0p833_0p833_0p167_0p167"],"t":769,"s":[0],"e":[100]},{"i":{"x":[0.833],"y":[0.833]},"o":{"x":[0.167],"y":[0.167]},"n":["0p833_0p833_0p167_0p167"],"t":775,"s":[100],"e":[0]},{"t":778}],"ix":7},"sk":{"a":0,"k":0,"ix":4},"sa":{"a":0,"k":0,"ix":5},"nm":"Transformar"}],"nm":"Grupo 8","np":2,"cix":2,"ix":8,"mn":"ADBE Vector Group","hd":false},{"ty":"gr","it":[{"ind":0,"ty":"sh","ix":1,"ks":{"a":0,"k":{"i":[[0,156.553],[-156.554,0],[0,-156.553],[156.553,0]],"o":[[0,-156.553],[156.553,0],[0,156.553],[-156.554,0]],"v":[[-283.464,0],[0,-283.465],[283.464,0],[0,283.465]],"c":true},"ix":2},"nm":"Trazado 1","mn":"ADBE Vector Shape - Group","hd":false},{"ty":"st","c":{"a":0,"k":[0.8,0.8,0.8,1],"ix":3},"o":{"a":0,"k":100,"ix":4},"w":{"a":0,"k":5.8,"ix":5},"lc":1,"lj":1,"ml":4,"ml2":{"a":0,"k":4,"ix":8},"nm":"Trazo 1","mn":"ADBE Vector Graphic - Stroke","hd":false},{"ty":"tr","p":{"a":1,"k":[{"i":{"x":0.667,"y":1},"o":{"x":0.167,"y":0.167},"n":"0p667_1_0p167_0p167","t":1.57,"s":[347.244,343.551],"e":[347.244,291.551],"to":[0,-8.66666698455811],"ti":[0,8.66666698455811]},{"t":240.958984375}],"ix":2},"a":{"a":0,"k":[0,0],"ix":1},"s":{"a":0,"k":[100,100],"ix":3},"r":{"a":0,"k":0,"ix":6},"o":{"a":1,"k":[{"i":{"x":[0.833],"y":[0.833]},"o":{"x":[0.167],"y":[0.167]},"n":["0p833_0p833_0p167_0p167"],"t":775,"s":[100],"e":[0]},{"i":{"x":[0.833],"y":[0.833]},"o":{"x":[0.167],"y":[0.167]},"n":["0p833_0p833_0p167_0p167"],"t":781,"s":[0],"e":[100]},{"i":{"x":[0.833],"y":[0.833]},"o":{"x":[0.167],"y":[0.167]},"n":["0p833_0p833_0p167_0p167"],"t":792,"s":[100],"e":[100]},{"i":{"x":[0.833],"y":[0.833]},"o":{"x":[0.167],"y":[0.167]},"n":["0p833_0p833_0p167_0p167"],"t":799,"s":[100],"e":[0]},{"i":{"x":[0.833],"y":[0.833]},"o":{"x":[0.167],"y":[0.167]},"n":["0p833_0p833_0p167_0p167"],"t":802,"s":[0],"e":[100]},{"i":{"x":[0.833],"y":[0.833]},"o":{"x":[0.167],"y":[0.167]},"n":["0p833_0p833_0p167_0p167"],"t":808,"s":[100],"e":[0]},{"t":811}],"ix":7},"sk":{"a":0,"k":0,"ix":4},"sa":{"a":0,"k":0,"ix":5},"nm":"Transformar"}],"nm":"Grupo 9","np":2,"cix":2,"ix":9,"mn":"ADBE Vector Group","hd":false},{"ty":"gr","it":[{"ind":0,"ty":"sh","ix":1,"ks":{"a":0,"k":{"i":[[0,172.208],[-172.208,0],[0,-172.208],[172.209,0]],"o":[[0,-172.208],[172.209,0],[0,172.208],[-172.208,0]],"v":[[-311.811,0],[0,-311.811],[311.811,0],[0,311.811]],"c":true},"ix":2},"nm":"Trazado 1","mn":"ADBE Vector Shape - Group","hd":false},{"ty":"st","c":{"a":0,"k":[0.8,0.8,0.8,1],"ix":3},"o":{"a":0,"k":100,"ix":4},"w":{"a":0,"k":5.9,"ix":5},"lc":1,"lj":1,"ml":4,"ml2":{"a":0,"k":4,"ix":8},"nm":"Trazo 1","mn":"ADBE Vector Graphic - Stroke","hd":false},{"ty":"tr","p":{"a":1,"k":[{"i":{"x":0.667,"y":1},"o":{"x":0.333,"y":0},"n":"0p667_1_0p333_0","t":1.57,"s":[347.244,345.897],"e":[347.244,320.897],"to":[0,-4.16666650772095],"ti":[0,4.16666650772095]},{"t":241}],"ix":2},"a":{"a":0,"k":[0,0],"ix":1},"s":{"a":0,"k":[100,100],"ix":3},"r":{"a":0,"k":0,"ix":6},"o":{"a":1,"k":[{"i":{"x":[0.833],"y":[0.833]},"o":{"x":[0.167],"y":[0.167]},"n":["0p833_0p833_0p167_0p167"],"t":610,"s":[100],"e":[0]},{"i":{"x":[0.833],"y":[0.833]},"o":{"x":[0.167],"y":[0.167]},"n":["0p833_0p833_0p167_0p167"],"t":616,"s":[0],"e":[100]},{"i":{"x":[0.833],"y":[0.833]},"o":{"x":[0.167],"y":[0.167]},"n":["0p833_0p833_0p167_0p167"],"t":627,"s":[100],"e":[100]},{"i":{"x":[0.833],"y":[0.833]},"o":{"x":[0.167],"y":[0.167]},"n":["0p833_0p833_0p167_0p167"],"t":634,"s":[100],"e":[0]},{"i":{"x":[0.833],"y":[0.833]},"o":{"x":[0.167],"y":[0.167]},"n":["0p833_0p833_0p167_0p167"],"t":637,"s":[0],"e":[100]},{"i":{"x":[0.833],"y":[0.833]},"o":{"x":[0.167],"y":[0.167]},"n":["0p833_0p833_0p167_0p167"],"t":643,"s":[100],"e":[0]},{"t":646}],"ix":7},"sk":{"a":0,"k":0,"ix":4},"sa":{"a":0,"k":0,"ix":5},"nm":"Transformar"}],"nm":"Grupo 10","np":2,"cix":2,"ix":10,"mn":"ADBE Vector Group","hd":false},{"ty":"gr","it":[{"ind":0,"ty":"sh","ix":1,"ks":{"a":0,"k":{"i":[[0,-187.864],[187.863,0],[0,187.864],[-187.864,0]],"o":[[0,187.864],[-187.864,0],[0,-187.864],[187.863,0]],"v":[[340.158,0],[0,340.157],[-340.158,0],[0,-340.157]],"c":true},"ix":2},"nm":"Trazado 1","mn":"ADBE Vector Shape - Group","hd":false},{"ty":"st","c":{"a":0,"k":[0.8,0.8,0.8,1],"ix":3},"o":{"a":0,"k":100,"ix":4},"w":{"a":0,"k":6,"ix":5},"lc":1,"lj":1,"ml":4,"ml2":{"a":0,"k":4,"ix":8},"nm":"Trazo 1","mn":"ADBE Vector Graphic - Stroke","hd":false},{"ty":"tr","p":{"a":0,"k":[347.244,347.244],"ix":2},"a":{"a":0,"k":[0,0],"ix":1},"s":{"a":0,"k":[100,100],"ix":3},"r":{"a":0,"k":0,"ix":6},"o":{"a":1,"k":[{"i":{"x":[0.833],"y":[0.833]},"o":{"x":[0.167],"y":[0.167]},"n":["0p833_0p833_0p167_0p167"],"t":707,"s":[100],"e":[0]},{"i":{"x":[0.833],"y":[0.833]},"o":{"x":[0.167],"y":[0.167]},"n":["0p833_0p833_0p167_0p167"],"t":713,"s":[0],"e":[100]},{"i":{"x":[0.833],"y":[0.833]},"o":{"x":[0.167],"y":[0.167]},"n":["0p833_0p833_0p167_0p167"],"t":724,"s":[100],"e":[100]},{"i":{"x":[0.833],"y":[0.833]},"o":{"x":[0.167],"y":[0.167]},"n":["0p833_0p833_0p167_0p167"],"t":731,"s":[100],"e":[0]},{"i":{"x":[0.833],"y":[0.833]},"o":{"x":[0.167],"y":[0.167]},"n":["0p833_0p833_0p167_0p167"],"t":734,"s":[0],"e":[100]},{"i":{"x":[0.833],"y":[0.833]},"o":{"x":[0.167],"y":[0.167]},"n":["0p833_0p833_0p167_0p167"],"t":740,"s":[100],"e":[0]},{"t":743}],"ix":7},"sk":{"a":0,"k":0,"ix":4},"sa":{"a":0,"k":0,"ix":5},"nm":"Transformar"}],"nm":"Grupo 11","np":2,"cix":2,"ix":11,"mn":"ADBE Vector Group","hd":false}],"ip":0,"op":3608,"st":0,"bm":0}]}],"layers":[{"ddd":0,"ind":2,"ty":0,"nm":"\rRecorrido del átomo 2","refId":"comp_0","sr":1,"ks":{"o":{"a":1,"k":[{"i":{"x":[0.833],"y":[0.833]},"o":{"x":[0.167],"y":[0.167]},"n":["0p833_0p833_0p167_0p167"],"t":7213,"s":[100],"e":[0]},{"t":7259}],"ix":11},"r":{"a":0,"k":180,"ix":10},"p":{"a":0,"k":[1220,1164,0],"ix":2},"a":{"a":0,"k":[320,320,0],"ix":1},"s":{"a":0,"k":[461,461,100],"ix":6}},"ao":0,"w":640,"h":640,"ip":7069,"op":7309,"st":7069,"bm":0},{"ddd":0,"ind":3,"ty":0,"nm":"Bouncerback gameSurface 2","refId":"comp_1","sr":1,"ks":{"o":{"a":1,"k":[{"i":{"x":[0.833],"y":[0.833]},"o":{"x":[0.167],"y":[0.167]},"n":["0p833_0p833_0p167_0p167"],"t":7259,"s":[100],"e":[0]},{"t":7320}],"ix":11},"r":{"a":1,"k":[{"i":{"x":[0.263],"y":[1.167]},"o":{"x":[0.677],"y":[0.001]},"n":["0p263_1p167_0p677_0p001"],"t":5280,"s":[0],"e":[720]},{"t":7200}],"ix":10},"p":{"a":1,"k":[{"i":{"x":0.833,"y":0.833},"o":{"x":0.167,"y":0.167},"n":"0p833_0p833_0p167_0p167","t":5280,"s":[796,140,0],"e":[676,256,0],"to":[-20,19.3333339691162,0],"ti":[0,0,0]},{"i":{"x":0.833,"y":0.833},"o":{"x":0.167,"y":0.167},"n":"0p833_0p833_0p167_0p167","t":5340,"s":[676,256,0],"e":[796,140,0],"to":[0,0,0],"ti":[0,0,0]},{"i":{"x":0.833,"y":0.833},"o":{"x":0.167,"y":0.167},"n":"0p833_0p833_0p167_0p167","t":5399,"s":[796,140,0],"e":[1836,-1700,0],"to":[0,0,0],"ti":[0,0,0]},{"i":{"x":0.833,"y":0.833},"o":{"x":0.167,"y":0.167},"n":"0p833_0p833_0p167_0p167","t":5400,"s":[1836,-1700,0],"e":[1013.611,-2505.578,0],"to":[0,0,0],"ti":[0,0,0]},{"i":{"x":0.833,"y":0.833},"o":{"x":0.167,"y":0.167},"n":"0p833_0p833_0p167_0p167","t":5460,"s":[1013.611,-2505.578,0],"e":[256,-764,0],"to":[0,0,0],"ti":[0,0,0]},{"i":{"x":0.833,"y":0.833},"o":{"x":0.167,"y":0.167},"n":"0p833_0p833_0p167_0p167","t":5519,"s":[256,-764,0],"e":[1956,-1208,0],"to":[0,0,0],"ti":[0,0,0]},{"i":{"x":0.833,"y":0.833},"o":{"x":0.167,"y":0.167},"n":"0p833_0p833_0p167_0p167","t":5520,"s":[1956,-1208,0],"e":[1740,-2324,0],"to":[0,0,0],"ti":[0,0,0]},{"i":{"x":0.833,"y":0.833},"o":{"x":0.167,"y":0.167},"n":"0p833_0p833_0p167_0p167","t":5579,"s":[1740,-2324,0],"e":[1000,316,0],"to":[0,0,0],"ti":[0,0,0]},{"i":{"x":0.833,"y":0.833},"o":{"x":0.167,"y":0.167},"n":"0p833_0p833_0p167_0p167","t":5580,"s":[1000,316,0],"e":[3540,-800,0],"to":[0,0,0],"ti":[0,0,0]},{"i":{"x":0.833,"y":0.833},"o":{"x":0.167,"y":0.167},"n":"0p833_0p833_0p167_0p167","t":5639,"s":[3540,-800,0],"e":[720,-572,0],"to":[0,0,0],"ti":[0,0,0]},{"i":{"x":0.833,"y":0.833},"o":{"x":0.167,"y":0.167},"n":"0p833_0p833_0p167_0p167","t":5640,"s":[720,-572,0],"e":[1424,236,0],"to":[0,0,0],"ti":[0,0,0]},{"i":{"x":0.833,"y":0.833},"o":{"x":0.167,"y":0.167},"n":"0p833_0p833_0p167_0p167","t":5759,"s":[1424,236,0],"e":[1280,-952,0],"to":[0,0,0],"ti":[0,0,0]},{"i":{"x":0.667,"y":1},"o":{"x":0.167,"y":0.167},"n":"0p667_1_0p167_0p167","t":5760,"s":[1280,-952,0],"e":[3116,32,0],"to":[0,0,0],"ti":[0,0,0]},{"i":{"x":0.816,"y":0.854},"o":{"x":0.328,"y":0},"n":"0p816_0p854_0p328_0","t":5820,"s":[3116,32,0],"e":[1856.321,-215.154,0],"to":[0,0,0],"ti":[0,0,0]},{"i":{"x":0.833,"y":0.833},"o":{"x":0.352,"y":0.005},"n":"0p833_0p833_0p352_0p005","t":5879,"s":[1856.321,-215.154,0],"e":[1495.823,948,0],"to":[0,0,0],"ti":[0,0,0]},{"i":{"x":0.833,"y":0.833},"o":{"x":0.167,"y":0.167},"n":"0p833_0p833_0p167_0p167","t":5880,"s":[1495.823,948,0],"e":[1422.012,627.454,0],"to":[0,0,0],"ti":[0,0,0]},{"i":{"x":0.833,"y":0.833},"o":{"x":0.167,"y":0.167},"n":"0p833_0p833_0p167_0p167","t":5940,"s":[1422.012,627.454,0],"e":[1826.879,1240.936,0],"to":[0,0,0],"ti":[0,0,0]},{"i":{"x":0.833,"y":0.833},"o":{"x":0.167,"y":0.167},"n":"0p833_0p833_0p167_0p167","t":5999,"s":[1826.879,1240.936,0],"e":[970.487,1744.622,0],"to":[0,0,0],"ti":[0,0,0]},{"i":{"x":0.833,"y":0.833},"o":{"x":0.167,"y":0.167},"n":"0p833_0p833_0p167_0p167","t":6000,"s":[970.487,1744.622,0],"e":[-159.638,1744.984,0],"to":[0,0,0],"ti":[0,0,0]},{"i":{"x":0.833,"y":0.833},"o":{"x":0.167,"y":0.167},"n":"0p833_0p833_0p167_0p167","t":6060,"s":[-159.638,1744.984,0],"e":[-103.348,1046.681,0],"to":[0,0,0],"ti":[0,0,0]},{"i":{"x":0.833,"y":0.833},"o":{"x":0.167,"y":0.167},"n":"0p833_0p833_0p167_0p167","t":6119,"s":[-103.348,1046.681,0],"e":[-198.394,-238.073,0],"to":[0,0,0],"ti":[0,0,0]},{"i":{"x":0.833,"y":0.833},"o":{"x":0.167,"y":0.167},"n":"0p833_0p833_0p167_0p167","t":6120,"s":[-198.394,-238.073,0],"e":[1648.187,-2043.956,0],"to":[0,0,0],"ti":[0,0,0]},{"i":{"x":0.833,"y":0.833},"o":{"x":0.167,"y":0.167},"n":"0p833_0p833_0p167_0p167","t":6180,"s":[1648.187,-2043.956,0],"e":[1606.528,-314.306,0],"to":[0,0,0],"ti":[0,0,0]},{"i":{"x":0.833,"y":0.833},"o":{"x":0.167,"y":0.167},"n":"0p833_0p833_0p167_0p167","t":6239,"s":[1606.528,-314.306,0],"e":[1721.823,710.263,0],"to":[0,0,0],"ti":[0,0,0]},{"i":{"x":0.833,"y":0.833},"o":{"x":0.167,"y":0.167},"n":"0p833_0p833_0p167_0p167","t":6240,"s":[1721.823,710.263,0],"e":[1672.206,680.37,0],"to":[0,0,0],"ti":[0,0,0]},{"i":{"x":0.833,"y":0.833},"o":{"x":0.167,"y":0.167},"n":"0p833_0p833_0p167_0p167","t":6300,"s":[1672.206,680.37,0],"e":[1623.417,650.975,0],"to":[0,0,0],"ti":[0,0,0]},{"i":{"x":0.833,"y":0.833},"o":{"x":0.167,"y":0.167},"n":"0p833_0p833_0p167_0p167","t":6359,"s":[1623.417,650.975,0],"e":[1438.59,1858.477,0],"to":[0,0,0],"ti":[0,0,0]},{"i":{"x":0.833,"y":0.833},"o":{"x":0.167,"y":0.167},"n":"0p833_0p833_0p167_0p167","t":6360,"s":[1438.59,1858.477,0],"e":[466.117,542.292,0],"to":[0,0,0],"ti":[0,0,0]},{"i":{"x":0.833,"y":0.833},"o":{"x":0.167,"y":0.167},"n":"0p833_0p833_0p167_0p167","t":6420,"s":[466.117,542.292,0],"e":[-86.945,-1561.18,0],"to":[0,0,0],"ti":[0,0,0]},{"i":{"x":0.833,"y":0.833},"o":{"x":0.167,"y":0.167},"n":"0p833_0p833_0p167_0p167","t":6479,"s":[-86.945,-1561.18,0],"e":[-1325.537,861.306,0],"to":[0,0,0],"ti":[0,0,0]},{"i":{"x":0.833,"y":0.833},"o":{"x":0.167,"y":0.167},"n":"0p833_0p833_0p167_0p167","t":6480,"s":[-1325.537,861.306,0],"e":[662.262,588.863,0],"to":[0,0,0],"ti":[0,0,0]},{"i":{"x":0.667,"y":1},"o":{"x":0.167,"y":0.167},"n":"0p667_1_0p167_0p167","t":6540,"s":[662.262,588.863,0],"e":[-24.109,282.804,0],"to":[0,0,0],"ti":[0,0,0]},{"i":{"x":0.666,"y":1},"o":{"x":0.333,"y":0},"n":"0p666_1_0p333_0","t":6599,"s":[-24.109,282.804,0],"e":[1123.891,-521.196,0],"to":[0,0,0],"ti":[0,0,0]},{"i":{"x":0.654,"y":0.989},"o":{"x":0.32,"y":0},"n":"0p654_0p989_0p32_0","t":6600,"s":[1123.891,-521.196,0],"e":[1663.506,-1380.334,0],"to":[0,0,0],"ti":[0,0,0]},{"i":{"x":0.66,"y":0.765},"o":{"x":0.325,"y":0.074},"n":"0p66_0p765_0p325_0p074","t":6660,"s":[1663.506,-1380.334,0],"e":[1688.582,-1245.313,0],"to":[0,0,0],"ti":[0,0,0]},{"i":{"x":0.667,"y":0.665},"o":{"x":0.333,"y":0.332},"n":"0p667_0p665_0p333_0p332","t":6719,"s":[1688.582,-1245.313,0],"e":[1687.843,-1243.877,0],"to":[0,0,0],"ti":[0,0,0]},{"i":{"x":0.664,"y":0.928},"o":{"x":0.326,"y":0.039},"n":"0p664_0p928_0p326_0p039","t":6720,"s":[1687.843,-1243.877,0],"e":[376.529,-264.59,0],"to":[0,0,0],"ti":[0,0,0]},{"i":{"x":0.667,"y":0.999},"o":{"x":0.333,"y":0.001},"n":"0p667_0p999_0p333_0p001","t":6839,"s":[376.529,-264.59,0],"e":[1263.182,-229.974,0],"to":[0,0,0],"ti":[0,0,0]},{"i":{"x":0.667,"y":1},"o":{"x":0.335,"y":0.106},"n":"0p667_1_0p335_0p106","t":6840,"s":[1263.182,-229.974,0],"e":[1223.218,328.779,0],"to":[0,0,0],"ti":[0,0,0]},{"i":{"x":0.663,"y":0.869},"o":{"x":0.333,"y":0},"n":"0p663_0p869_0p333_0","t":6900,"s":[1223.218,328.779,0],"e":[1071.438,168.766,0],"to":[0,0,0],"ti":[0,0,0]},{"i":{"x":0.667,"y":1},"o":{"x":0.333,"y":0},"n":"0p667_1_0p333_0","t":6959,"s":[1071.438,168.766,0],"e":[150.11,-518.649,0],"to":[0,0,0],"ti":[0,0,0]},{"i":{"x":0.671,"y":0.969},"o":{"x":0.335,"y":0.013},"n":"0p671_0p969_0p335_0p013","t":6960,"s":[150.11,-518.649,0],"e":[1848.401,-2020.22,0],"to":[0,0,0],"ti":[0,0,0]},{"i":{"x":0.68,"y":0.522},"o":{"x":0.343,"y":0.153},"n":"0p68_0p522_0p343_0p153","t":7020,"s":[1848.401,-2020.22,0],"e":[1671.733,-1587.912,0],"to":[0,0,0],"ti":[0,0,0]},{"i":{"x":0.667,"y":0.998},"o":{"x":0.334,"y":0.002},"n":"0p667_0p998_0p334_0p002","t":7079,"s":[1671.733,-1587.912,0],"e":[235.245,-688.932,0],"to":[0,0,0],"ti":[0,0,0]},{"i":{"x":0.667,"y":1},"o":{"x":0.358,"y":0.14},"n":"0p667_1_0p358_0p14","t":7080,"s":[235.245,-688.932,0],"e":[1253.29,829.632,0],"to":[0,0,0],"ti":[0,0,0]},{"i":{"x":0.833,"y":0.833},"o":{"x":0.333,"y":0},"n":"0p833_0p833_0p333_0","t":7140,"s":[1253.29,829.632,0],"e":[1152,648,0],"to":[0,0,0],"ti":[0,0,0]},{"i":{"x":0.833,"y":0.833},"o":{"x":0.167,"y":0.167},"n":"0p833_0p833_0p167_0p167","t":7200,"s":[1152,648,0],"e":[1172,1068,0],"to":[0,0,0],"ti":[0,0,0]},{"t":7300}],"ix":2},"a":{"a":0,"k":[340,35,0],"ix":1},"s":{"a":1,"k":[{"i":{"x":[0.833,0.833,0.833],"y":[0.833,0.833,0.833]},"o":{"x":[0.167,0.167,0.167],"y":[0.167,0.167,0.167]},"n":["0p833_0p833_0p167_0p167","0p833_0p833_0p167_0p167","0p833_0p833_0p167_0p167"],"t":5280,"s":[461,461,100],"e":[461,461,100]},{"t":7200}],"ix":6}},"ao":0,"tm":{"a":1,"k":[{"i":{"x":[0.833],"y":[0.833]},"o":{"x":[0.167],"y":[0.167]},"n":["0p833_0p833_0p167_0p167"],"t":5280,"s":[0],"e":[3.983]},{"t":5518}],"ix":2,"x":"var $bm_rt;\n$bm_rt = loopOut('cycle');"},"w":680,"h":680,"ip":5280,"op":7485,"st":5280,"bm":0},{"ddd":0,"ind":4,"ty":0,"nm":"Looped gameSurface","refId":"comp_2","sr":1,"ks":{"o":{"a":1,"k":[{"i":{"x":[0.833],"y":[0.833]},"o":{"x":[0.167],"y":[0.167]},"n":["0p833_0p833_0p167_0p167"],"t":1438,"s":[0],"e":[100]},{"t":1468}],"ix":11},"r":{"a":1,"k":[{"i":{"x":[0.667],"y":[1]},"o":{"x":[0.333],"y":[0]},"n":["0p667_1_0p333_0"],"t":2398,"s":[0],"e":[60]},{"i":{"x":[0.717],"y":[1]},"o":{"x":[0.303],"y":[0]},"n":["0p717_1_0p303_0"],"t":2638,"s":[60],"e":[60]},{"i":{"x":[0.773],"y":[1]},"o":{"x":[0.423],"y":[0]},"n":["0p773_1_0p423_0"],"t":3120,"s":[60],"e":[120]},{"i":{"x":[0.833],"y":[1]},"o":{"x":[0.167],"y":[0]},"n":["0p833_1_0p167_0"],"t":3240,"s":[120],"e":[120]},{"i":{"x":[0.833],"y":[1]},"o":{"x":[0.167],"y":[0]},"n":["0p833_1_0p167_0"],"t":3360,"s":[120],"e":[40]},{"t":5280}],"ix":10},"p":{"a":1,"k":[{"i":{"x":0.833,"y":0.833},"o":{"x":0.167,"y":0.167},"n":"0p833_0p833_0p167_0p167","t":1438,"s":[960,540,0],"e":[960,2527,0],"to":[0,331.166656494141,0],"ti":[240.66667175293,-205.83332824707,0]},{"i":{"x":0.667,"y":1},"o":{"x":0.167,"y":0.167},"n":"0p667_1_0p167_0p167","t":1558,"s":[960,2527,0],"e":[-484,1775,0],"to":[-240.66667175293,205.83332824707,0],"ti":[-241.83332824707,479.666656494141,0]},{"i":{"x":0.667,"y":1},"o":{"x":0.333,"y":0},"n":"0p667_1_0p333_0","t":1678,"s":[-484,1775,0],"e":[2411,-351,0],"to":[241.83332824707,-479.666656494141,0],"ti":[-258.5,205,0]},{"i":{"x":0.667,"y":1},"o":{"x":0.333,"y":0},"n":"0p667_1_0p333_0","t":1918,"s":[2411,-351,0],"e":[1067,545,0],"to":[258.5,-205,0],"ti":[224,-149.33332824707,0]},{"i":{"x":0.667,"y":0.667},"o":{"x":0.333,"y":0.333},"n":"0p667_0p667_0p333_0p333","t":2038,"s":[1067,545,0],"e":[1067,545,0],"to":[0,0,0],"ti":[0,0,0]},{"i":{"x":0.667,"y":1},"o":{"x":0.333,"y":0},"n":"0p667_1_0p333_0","t":2155,"s":[1067,545,0],"e":[995,-1311,0],"to":[-12,-309.333343505859,0],"ti":[290.666656494141,-185.33332824707,0]},{"i":{"x":0.667,"y":0.549},"o":{"x":0.333,"y":0},"n":"0p667_0p549_0p333_0","t":2280,"s":[995,-1311,0],"e":[-581.993,-424.535,0],"to":[-148.75520324707,94.8484954833984,0],"ti":[354.811157226562,-674.056396484375,0]},{"i":{"x":0.667,"y":1},"o":{"x":0.333,"y":0.411},"n":"0p667_1_0p333_0p411","t":2338,"s":[-581.993,-424.535,0],"e":[-677,1657,0],"to":[-338.487487792969,643.045288085938,0],"ti":[136.052734375,-241.509887695312,0]},{"i":{"x":0.667,"y":0.937},"o":{"x":0.333,"y":0},"n":"0p667_0p937_0p333_0","t":2398,"s":[-677,1657,0],"e":[1021.345,569.851,0],"to":[-118.043785095215,209.541839599609,0],"ti":[-18.4257106781006,32.7078399658203,0]},{"i":{"x":0.667,"y":1},"o":{"x":0.333,"y":0.068},"n":"0p667_1_0p333_0p068","t":2522,"s":[1021.345,569.851,0],"e":[2523,1553,0],"to":[25.0719738006592,-44.5057525634766,0],"ti":[0,0,0]},{"i":{"x":0.667,"y":1},"o":{"x":0.333,"y":0},"n":"0p667_1_0p333_0","t":2638,"s":[2523,1553,0],"e":[-921,-627,0],"to":[0,0,0],"ti":[0,0,0]},{"i":{"x":0.667,"y":0.599},"o":{"x":0.333,"y":0},"n":"0p667_0p599_0p333_0","t":2879,"s":[-921,-627,0],"e":[-1309.354,812.104,0],"to":[0,0,0],"ti":[0,0,0]},{"i":{"x":0.667,"y":1},"o":{"x":0.333,"y":0.603},"n":"0p667_1_0p333_0p603","t":2942,"s":[-1309.354,812.104,0],"e":[-997,1669,0],"to":[0,0,0],"ti":[0,0,0]},{"i":{"x":0.667,"y":1},"o":{"x":0.333,"y":0},"n":"0p667_1_0p333_0","t":3000,"s":[-997,1669,0],"e":[-829,-519,0],"to":[0,0,0],"ti":[0,0,0]},{"i":{"x":0.667,"y":1},"o":{"x":0.333,"y":0},"n":"0p667_1_0p333_0","t":3120,"s":[-829,-519,0],"e":[-621,-647,0],"to":[0,0,0],"ti":[0,0,0]},{"i":{"x":0.667,"y":1},"o":{"x":0.333,"y":0},"n":"0p667_1_0p333_0","t":3240,"s":[-621,-647,0],"e":[923,2529,0],"to":[0,0,0],"ti":[0,0,0]},{"i":{"x":0.667,"y":0.994},"o":{"x":0.333,"y":0},"n":"0p667_0p994_0p333_0","t":3360,"s":[923,2529,0],"e":[811.221,251.18,0],"to":[0,0,0],"ti":[0,0,0]},{"i":{"x":0.648,"y":0.957},"o":{"x":0.314,"y":0.052},"n":"0p648_0p957_0p314_0p052","t":3479,"s":[811.221,251.18,0],"e":[940.741,473.854,0],"to":[0,0,0],"ti":[0,0,0]},{"i":{"x":0.667,"y":0.999},"o":{"x":0.333,"y":0.001},"n":"0p667_0p999_0p333_0p001","t":3599,"s":[940.741,473.854,0],"e":[856.528,481.7,0],"to":[0,0,0],"ti":[0,0,0]},{"i":{"x":0.649,"y":0.996},"o":{"x":0.315,"y":0.004},"n":"0p649_0p996_0p315_0p004","t":3600,"s":[856.528,481.7,0],"e":[2917.419,1273.926,0],"to":[0,0,0],"ti":[0,0,0]},{"i":{"x":0.66,"y":0.683},"o":{"x":0.323,"y":0.001},"n":"0p66_0p683_0p323_0p001","t":3718,"s":[2917.419,1273.926,0],"e":[1936.104,-1433.498,0],"to":[0,0,0],"ti":[0,0,0]},{"i":{"x":0.67,"y":0.983},"o":{"x":0.333,"y":0.831},"n":"0p67_0p983_0p333_0p831","t":3780,"s":[1936.104,-1433.498,0],"e":[877.095,-1472.152,0],"to":[0,0,0],"ti":[0,0,0]},{"i":{"x":0.664,"y":0.983},"o":{"x":0.331,"y":0.015},"n":"0p664_0p983_0p331_0p015","t":3841,"s":[877.095,-1472.152,0],"e":[-925.923,155.034,0],"to":[0,0,0],"ti":[0,0,0]},{"i":{"x":0.652,"y":0.957},"o":{"x":0.316,"y":0.023},"n":"0p652_0p957_0p316_0p023","t":3959,"s":[-925.923,155.034,0],"e":[2567.034,394.604,0],"to":[0,0,0],"ti":[0,0,0]},{"i":{"x":0.659,"y":0.892},"o":{"x":0.324,"y":0.09},"n":"0p659_0p892_0p324_0p09","t":4200,"s":[2567.034,394.604,0],"e":[1039.784,694.898,0],"to":[0,0,0],"ti":[0,0,0]},{"i":{"x":0.521,"y":0.982},"o":{"x":0.163,"y":0.031},"n":"0p521_0p982_0p163_0p031","t":4439,"s":[1039.784,694.898,0],"e":[2085.629,1480.499,0],"to":[0,0,0],"ti":[0,0,0]},{"i":{"x":0.633,"y":0.933},"o":{"x":0.294,"y":0.01},"n":"0p633_0p933_0p294_0p01","t":4561,"s":[2085.629,1480.499,0],"e":[1029.149,556.044,0],"to":[0,0,0],"ti":[0,0,0]},{"i":{"x":0.482,"y":0.987},"o":{"x":0.101,"y":0.027},"n":"0p482_0p987_0p101_0p027","t":4679,"s":[1029.149,556.044,0],"e":[226.792,-34.983,0],"to":[0,0,0],"ti":[0,0,0]},{"i":{"x":0.64,"y":0.799},"o":{"x":0.297,"y":0.013},"n":"0p64_0p799_0p297_0p013","t":4800,"s":[226.792,-34.983,0],"e":[371.761,486.683,0],"to":[0,0,0],"ti":[0,0,0]},{"i":{"x":0.69,"y":0.821},"o":{"x":0.33,"y":0.347},"n":"0p69_0p821_0p33_0p347","t":4920,"s":[371.761,486.683,0],"e":[941.081,553.168,0],"to":[0,0,0],"ti":[0,0,0]},{"i":{"x":0.733,"y":0.997},"o":{"x":0.127,"y":1},"n":"0p733_0p997_0p127_1","t":5159,"s":[941.081,553.168,0],"e":[943,532,0],"to":[0,0,0],"ti":[0,0,0]},{"t":5280}],"ix":2},"a":{"a":0,"k":[340,340,0],"ix":1},"s":{"a":1,"k":[{"i":{"x":[0.833,0.833,0.833],"y":[0.833,0.833,0.833]},"o":{"x":[0.167,0.167,0.167],"y":[0.167,0.167,0.167]},"n":["0p833_0p833_0p167_0p167","0p833_0p833_0p167_0p167","0p833_0p833_0p167_0p167"],"t":1438,"s":[1,1,100],"e":[717,717,100]},{"i":{"x":[0.833,0.833,0.833],"y":[0.833,0.833,0.833]},"o":{"x":[0.167,0.167,0.167],"y":[0.167,0.167,0.167]},"n":["0p833_0p833_0p167_0p167","0p833_0p833_0p167_0p167","0p833_0p833_0p167_0p167"],"t":1468,"s":[717,717,100],"e":[717,717,100]},{"i":{"x":[0.833,0.833,0.833],"y":[1,1,1]},"o":{"x":[0.167,0.167,0.167],"y":[0,0,0]},"n":["0p833_1_0p167_0","0p833_1_0p167_0","0p833_1_0p167_0"],"t":3240,"s":[717,717,100],"e":[717,717,100]},{"i":{"x":[0.82,0.82,0.667],"y":[0.831,0.831,1.064]},"o":{"x":[0.776,0.776,0.333],"y":[0.019,0.019,0]},"n":["0p82_0p831_0p776_0p019","0p82_0p831_0p776_0p019","0p667_1p064_0p333_0"],"t":3361,"s":[717,717,100],"e":[239.739,239.739,100]},{"i":{"x":[0.629,0.629,0.667],"y":[0.997,0.997,1]},"o":{"x":[0.301,0.301,0.333],"y":[0.093,0.093,-0.004]},"n":["0p629_0p997_0p301_0p093","0p629_0p997_0p301_0p093","0p667_1_0p333_-0p004"],"t":5159,"s":[239.739,239.739,100],"e":[142.196,142.196,100]},{"t":5280}],"ix":6}},"ao":0,"tm":{"a":1,"k":[{"i":{"x":[0.833],"y":[0.833]},"o":{"x":[0.167],"y":[0.167]},"n":["0p833_0p833_0p167_0p167"],"t":1438,"s":[0],"e":[8]},{"t":1919}],"ix":2,"x":"var $bm_rt;\n$bm_rt = loopOut('cycle');"},"w":680,"h":680,"ip":1438,"op":5280,"st":1438,"bm":0},{"ddd":0,"ind":5,"ty":0,"nm":"Esferas","refId":"comp_5","sr":1,"ks":{"o":{"a":1,"k":[{"i":{"x":[0.833],"y":[0.833]},"o":{"x":[0.167],"y":[0.167]},"n":["0p833_0p833_0p167_0p167"],"t":0,"s":[0],"e":[100]},{"i":{"x":[0.833],"y":[0.833]},"o":{"x":[0.167],"y":[0.167]},"n":["0p833_0p833_0p167_0p167"],"t":235,"s":[100],"e":[100]},{"i":{"x":[0.833],"y":[0.833]},"o":{"x":[0.167],"y":[0.167]},"n":["0p833_0p833_0p167_0p167"],"t":478,"s":[100],"e":[100]},{"i":{"x":[0.833],"y":[0.833]},"o":{"x":[0.167],"y":[0.167]},"n":["0p833_0p833_0p167_0p167"],"t":1214,"s":[100],"e":[0]},{"t":1448}],"ix":11},"r":{"a":0,"k":0,"ix":10},"p":{"a":0,"k":[960,540,0],"ix":2},"a":{"a":0,"k":[960,540,0],"ix":1},"s":{"a":1,"k":[{"i":{"x":[0.384,0.384,0.667],"y":[0.997,0.997,1]},"o":{"x":[0.591,0.591,0.333],"y":[0.003,0.003,0]},"n":["0p384_0p997_0p591_0p003","0p384_0p997_0p591_0p003","0p667_1_0p333_0"],"t":478,"s":[100,100,100],"e":[972,972,100]},{"t":1447}],"ix":6}},"ao":0,"w":1920,"h":1080,"ip":0,"op":1478,"st":0,"bm":0}],"markers":[]}